{"date": "2005-10-07", "author": "bencomic", "panels": [{"background": "images/backgrounds/misc/splitter.jpg", "dialog": {"right": {"text": "why is that in caps", "type": "dialog"}, "left": {"text": "And it is against Catholicism to accept homosexuALITY as being \"ok\" because it's NOT. Yes, you can accept your friends and people who are, but you can't accept when they're doing. God won't either.", "type": "dialog"}}, "characters": {"right": "images/kaddar2/geek-cripple-r.gif", "left": "images/kaddar2/geek-cripple-r.gif"}}, {"background": "images/backgrounds/misc/splitter.jpg", "dialog": {"right": {"text": "but with gay sex instead of killing", "type": "dialog"}, "left": {"text": "it's like a fatality", "type": "dialog"}}, "characters": {"right": "images/kaddar/redhat-l.gif", "left": "images/kaddar/redhat-l.gif"}}, {"background": "images/backgrounds/misc/splitter.jpg", "dialog": {"right": {"text": "    ;)", "type": "dialog"}, "left": {"text": "FINISH HIM!", "type": "dialog"}}, "characters": {"right": "images/kaddar/redhat-l.gif", "left": "images/kaddar/redhat-l.gif"}}], "sc_id": 315142, "title": "GET OVER HERE!"}