{"date": "2005-10-12", "author": "bencomic", "panels": [{"background": "images/backgrounds/inside/sale.jpg", "dialog": {"right": {"text": "nnoo itsn not a bprinak........ mmgogoobdye e;lli", "type": "dialog"}, "left": {"text": "is this a stupid prank?", "type": "dialog"}}, "characters": {"right": "images/threereasons/feetforears2.gif", "left": "images/kaddar2/kid_ck_r.gif"}}, {"background": "images/backgrounds/inside/sale.jpg", "dialog": {"right": {"text": "eli why the fuck would we be joking about something like that?", "type": "dialog"}, "left": {"text": "we'd be some pretty horrible people to play such a prank :(", "type": "dialog"}}, "characters": {"right": "images/kofightclub/holly_punch1.gif", "left": "images/kaddar2/geek-cripple-l.gif"}}, {"background": "images/backgrounds/misc/black.jpg", "dialog": {"right": {"text": "iiif i siee god ]ill tekkll him hi foor u :(((999;;;", "type": "dialog"}, "left": {"text": "", "type": "dialog"}}, "characters": {"right": "images/threereasons/feetforears2.gif", "left": "images/none/none.gif"}}], "sc_id": 315877, "title": "JAZZ ODYSSEY part 6"}