{"date": "2005-10-22", "author": "bencomic", "panels": [{"background": "images/backgrounds/inside/bar.jpg", "dialog": {"right": {"text": "so will duke nukem forever!!!", "type": "dialog"}, "left": {"text": "It'll be release this Summer", "type": "dialog"}}, "characters": {"right": "images/submitted/lizardsuit2.gif", "left": "images/holiday/dracula4-l.gif"}}, {"background": "images/backgrounds/fantasy/hauntedhouse.jpg", "dialog": {"right": {"text": "i want proof now. give me proof that it exists", "type": "dialog"}, "left": {"text": "Just wait", "type": "dialog"}}, "characters": {"right": "images/explodingdog/itoldyou1-2.gif", "left": "images/holiday/dracula3-l.gif"}}, {"background": "images/backgrounds/inside/bedroom.jpg", "dialog": {"right": {"text": "waiting is not good proof", "type": "dialog"}, "left": {"text": "Wait. It will be released", "type": "dialog"}}, "characters": {"right": "images/explodingdog/hammer2-2.gif", "left": "images/holiday/dracula3-r.gif"}}], "sc_id": 318258, "title": "watch doom3 in action part 19"}