{"date": "2006-01-30", "author": "bencomic", "panels": [{"background": "images/backgrounds/urban/buildings.jpg", "dialog": {"right": {"text": "quantum tell her you've got a very big present for her", "type": "dialog"}, "left": {"text": "today's the birthday of a girl i like", "type": "dialog"}}, "characters": {"right": "images/whenigrowup/wiguroger1-2.gif", "left": "images/kaddar2/gnome-r.gif"}}, {"background": "images/backgrounds/misc/splitter.jpg", "dialog": {"right": {"text": ":o", "type": "dialog"}, "left": {"text": "and point to your crotch", "type": "dialog"}}, "characters": {"right": "images/kaddar2/gnome-l.gif", "left": "images/whenigrowup/wiguroger1-1.gif"}}, {"background": "images/backgrounds/rural/rocks.jpg", "narration": "LATER THAT DAY", "dialog": {"right": {"text": ";)", "type": "thought"}, "left": {"text": "what the", "type": "dialog"}}, "characters": {"right": "images/kaddar2/gnome-l.gif", "left": "images/kaddar2/schoolgirl-r.gif"}}], "sc_id": 335339, "title": "QUANTUM PENIS"}