{"date": "2006-02-04", "author": "bencomic", "panels": [{"background": "images/backgrounds/misc/splitter.jpg", "dialog": {"right": {"text": "I'd like to ask you what you think of the recent move to the slightly less stable espernet, and if you think Kracken may have been a bit tyrannic in this move.", "type": "dialog"}, "left": {"text": "Hello drac0. Im doing an interview for WMZX.", "type": "dialog"}}, "characters": {"right": "images/kaddar/bull-r.gif", "left": "images/kaddar/bull-r.gif"}}, {"background": "images/backgrounds/misc/explosion.jpg", "dialog": {"right": {"text": "in the right of censorship, i have to change GAY to STUPID.", "type": "dialog"}, "left": {"text": "GAY", "type": "dialog"}}, "characters": {"right": "images/kaddar/bull-l.gif", "left": "images/forumusers/dragonxero1.gif"}}, {"background": "images/backgrounds/house/dooropenint-r.jpg", "dialog": {"right": {"text": "goodbye", "type": "dialog"}, "left": {"text": "im sorry for any inconvience this may cause", "type": "dialog"}}, "characters": {"right": "images/kaddar/bull-r.gif", "left": "images/kaddar/bull-l.gif"}}], "sc_id": 336166, "title": "in the right of censorship"}