{"date": "2006-02-27", "author": "bencomic", "panels": [{"background": "images/backgrounds/misc/blacker.jpg", "dialog": {"right": {"text": "\"Oh no!\" exclaimed C-3PO, before Tom interjected \"SHUT THE FUCK UP YOU FAGGOT PIECE OF SHIT.\"", "type": "dialog"}, "left": {"text": "haha yes! i bet you put yourself in them", "type": "dialog"}}, "characters": {"right": "images/threereasons/asiangirl1-2.gif", "left": "images/threereasons/asiangirl1.gif"}}, {"background": "images/backgrounds/fantasy/psycho.jpg", "dialog": {"right": {"text": "HRAHLHFLSHFAS fASLDSHAJDWHA DQ", "type": "dialog"}, "left": {"text": "NO!!!! N O!!!!!!! NEVER EVER", "type": "dialog"}}, "characters": {"right": "images/submitted/sharkman.gif", "left": "images/submitted/sharkman2.gif"}}, {"background": "images/backgrounds/fantasy/planet.jpg", "dialog": {"right": {"text": "FUCK YOU!!!! FUUUUUUUUUCK YOOOOOOOOOOOOUUUUU", "type": "dialog"}, "left": {"text": "and i bet you tried to find the biblical references in it", "type": "dialog"}}, "characters": {"right": "images/submitted/sharkman2.gif", "left": "images/threereasons/asiangirl1.gif"}}], "sc_id": 339723, "title": "star bores part 2"}