{"date": "2007-12-30", "author": "bencomic", "panels": [{"background": "images/backgrounds/office/lounge.jpg", "dialog": {"right": {"text": "goatse man ascii, discuss", "type": "dialog"}, "left": {"text": "( 3*E )/ /u\\ \\", "type": "dialog"}}, "characters": {"right": "images/submitted/mrstinkybutt1-1.gif", "left": "images/submitted/mrstinkybutt1-1.gif"}}, {"background": "images/backgrounds/office/lounge.jpg", "dialog": {"right": {"text": "spiderman isnt the only one who gets his hands sticky on the web", "type": "dialog"}, "left": {"text": "you suck", "type": "dialog"}}, "characters": {"right": "images/submitted/mrstinkybutt1-2.gif", "left": "images/choppingblock/victim2-1.gif"}}, {"background": "images/backgrounds/misc/motionblur.jpg", "dialog": {"right": {"text": "YOU SUCK BIG FAT MONKEY DICK, FUCKING DONKEY PORKER", "type": "dialog"}, "left": {"text": "you suck", "type": "dialog"}}, "characters": {"right": "images/submitted/mrstinkybutt1-1.gif", "left": "images/choppingblock/victim2-1.gif"}}], "sc_id": 417324, "title": "the saga of chairface chippendale, part 3"}